setup.cfg
setup.py
pogotransfercalc/__init__.py
pogotransfercalc/calculate.py
pogotransfercalc/cost.py
pogotransfercalc.egg-info/PKG-INFO
pogotransfercalc.egg-info/SOURCES.txt
pogotransfercalc.egg-info/dependency_links.txt
pogotransfercalc.egg-info/top_level.txt