Metadata-Version: 1.1
Name: pogotransfercalc
Version: 1.0.2
Summary: Easily calculate how many Pokémon you should transfer before kicking off an evolution spree in Pokémon GO
Home-page: https://github.com/mathiasbynens/pogotransfercalc
Author: Mathias Bynens
Author-email: mathias@qiwi.be
License: MIT
Download-URL: https://github.com/mathiasbynens/pogotransfercalc/tarball/v1.0.2
Keywords: pogo,pokemon go
Platform: UNKNOWN
Classifier: Development Status :: 5 - Production/Stable
Classifier: Intended Audience :: Developers
Classifier: License :: OSI Approved :: MIT License
Classifier: Operating System :: MacOS :: MacOS X
Classifier: Operating System :: Microsoft :: Windows
Classifier: Operating System :: POSIX :: Linux
Classifier: Operating System :: POSIX
Classifier: Programming Language :: Python :: 2.6
Classifier: Programming Language :: Python :: 2.7
Classifier: Programming Language :: Python :: 3.3
Classifier: Programming Language :: Python :: 3.4
Classifier: Programming Language :: Python :: 3.5
Classifier: Programming Language :: Python :: Implementation :: PyPy
Classifier: Topic :: Software Development :: Libraries
